LICENSE
README.md
setup.py
DeepCoreML/Classifiers.py
DeepCoreML/DataAnimator.py
DeepCoreML/Dataset.py
DeepCoreML/Resamplers.py
DeepCoreML/ResultHandler.py
DeepCoreML/TabularDataset.py
DeepCoreML/TabularTransformer.py
DeepCoreML/Tools.py
DeepCoreML/__init__.py
DeepCoreML/eval.py
DeepCoreML/main_imbalanced.py
DeepCoreML/paths.py
DeepCoreML.egg-info/PKG-INFO
DeepCoreML.egg-info/SOURCES.txt
DeepCoreML.egg-info/dependency_links.txt
DeepCoreML.egg-info/requires.txt
DeepCoreML.egg-info/top_level.txt
DeepCoreML/generators/GAN_Synthesizer.py
DeepCoreML/generators/__init__.py
DeepCoreML/generators/c_gan.py
DeepCoreML/generators/cbr.py
DeepCoreML/generators/ct_gan.py
DeepCoreML/generators/ctabgan_synthesizer.py
DeepCoreML/generators/ctabgan_transformer.py
DeepCoreML/generators/ctabganplus_synthesizer.py
DeepCoreML/generators/ctabganplus_transformer.py
DeepCoreML/generators/ctd_clusterer.py
DeepCoreML/generators/ctd_discretizer.py
DeepCoreML/generators/ctd_gan.py
DeepCoreML/generators/ctd_gan_discretizer.py
DeepCoreML/generators/fctgan_synthesizer.py
DeepCoreML/generators/fctgan_transformer.py
DeepCoreML/generators/fno.py
DeepCoreML/generators/gan_discriminators.py
DeepCoreML/generators/gan_generators.py
DeepCoreML/generators/gmm_gan_subspaces.py
DeepCoreML/generators/sb_gan.py